CHANGELOG.rst
LICENSE
MANIFEST.in
README.rst
requirements.txt
setup.py
frags/FindRecombinationsAmongGenomes.py
frags/__init__.py
frags/context.py
frags/core.py
frags/read.py
frags.egg-info/PKG-INFO
frags.egg-info/SOURCES.txt
frags.egg-info/dependency_links.txt
frags.egg-info/entry_points.txt
frags.egg-info/requires.txt
frags.egg-info/top_level.txt
tests/__init__.py
tests/context.py
tests/test_FindRecombinationsAmongGenomes.py
tests/test_core.py
tests/test_functional.py
tests/test_read.py