Metadata-Version: 2.1
Name: frags
Version: 0.1.5
Summary: Finding recombinations in reads
Home-page: https://gitlab.pasteur.fr/nmaillet/frags
Author: Maillet Nicolas
Author-email: nicolas.maillet@pasteur.fr
License: UNKNOWN
Project-URL: Doc, https://frags.readthedocs.io/en/latest/
Keywords: reads,recombination,chimeric,virus,genomes
Platform: UNKNOWN
Classifier: Development Status :: 4 - Beta
Classifier: Intended Audience :: Science/Research
Classifier: Topic :: Scientific/Engineering :: Bio-Informatics
Classifier: License :: OSI Approved :: GNU General Public License v3 or later (GPLv3+)
Classifier: Programming Language :: Python :: 3.7
Classifier: Programming Language :: Python :: 3.8
Classifier: Programming Language :: Python :: 3.9
Requires-Python: >=3.7
Provides-Extra: test
